<?xml version="1.0" ?><constants>	<constant>		<name>ul_padding_top</name>		<value>25px</value>	</constant>	<constant>		<name>ul_padding_right</name>		<value>42px</value>	</constant>	<constant>		<name>ul_padding_bottom</name>		<value>17px</value>	</constant>	<constant>		<name>ul_padding_left</name>		<value>22px</value>	</constant>	<constant>		<name>ul_width</name>		<value>7em</value>	</constant>	<constant>		<name>sub_li_top</name>		<value>5em</value>	</constant></constants>